Workbook

Sheet Raw Data
A1: Transaction_ID | B1: Year | C1: Quarter | D1: Product | E1: Revenue | F1: Cost | G1: Profit
A2: TXN-1000 | B2: 2023 | C2: Q1 | D2: Widget Pro | E2: 15819 | F2: 9196.41 | G2: 6622.59
A3: TXN-1001 | B3: 2023 | C3: Q1 | D3: Widget Pro | E3: 23024 | F3: 15294.53 | G3: 7729.47
A4: TXN-1002 | B4: 2023 | C4: Q1 | D4: Widget Pro | E4: 39132 | F4: 26750.67 | G4: 12381.33
A5: TXN-1003 | B5: 2023 | C5: Q1 | D5: Widget Pro | E5: 39270 | F5: 21883.26 | G5: 17386.74
A6: TXN-1004 | B6: 2023 | C6: Q1 | D6: Widget Standard | E6: 21825 | F6: 16940.26 | G6: 4884.74
A7: TXN-1005 | B7: 2023 | C7: Q1 | D7: Widget Standard | E7: 11070 | F7: 8344.16 | G7: 2725.84
A8: TXN-1006 | B8: 2023 | C8: Q1 | D8: Widget Standard | E8: 24559 | F8: 17381.82 | G8: 7177.18
A9: TXN-1007 | B9: 2023 | C9: Q1 | D9: Widget Standard | E9: 14515 | F9: 10074.54 | G9: 4440.46
A10: TXN-1008 | B10: 2023 | C10: Q1 | D10: Service Package | E10: 11873 | F10: 7193.99 | G10: 4679.01
A11: TXN-1009 | B11: 2023 | C11: Q1 | D11: Service Package | E11: 14654 | F11: 8709.78 | G11: 5944.22
A12: TXN-1010 | B12: 2023 | C12: Q1 | D12: Service Package | E12: 19242 | F12: 12482.29 | G12: 6759.71
A13: TXN-1011 | B13: 2023 | C13: Q1 | D13: Service Package | E13: 18202 | F13: 11250.08 | G13: 6951.92
... A187: TXN-1185 | B187: 2024 | C187: Q4 | D187: Accessory Kit | E187: 3864 | F187: 3198.26 | G187: 665.74

Sheet Dashboard
A1: Executive Sales Performance Dashboard
A3: Instructions: Complete the analysis below using the Raw Data tab. All calculations should use formulas.
A5: Quarterly Performance Summary
A7: Product | B7: Quarter | C7: Total Revenue | D7: Weighted Avg Margin | E7: Rolling 3-Mo Trend | F7: YoY Margin Delta | G7: Margin Health
A8: Widget Pro | B8: 2023 Q1 | C8: =SUMIFS('Raw Data'!E:E, 'Raw Data'!D:D, A8, 'Raw Data'!B:B, LEFT(B8,4), 'Raw Data'!C:C, RIGHT(B8,2)) -> 117245 | D8: {=SUMPRODUCT(('Raw Data'!$D$2:$D$500=A8)*('Raw Data'!$B$2:$B$500&" "&'Raw Data'!$C$2:$C$500=B8)*('Raw Data'!$G$2:$G$500))/C8} -> 0.37630713 | E8: =IF(B8="2023 Q1", "N/A", D8-D7) -> N/A | F8: {=IF(LEFT(B8, 4)="2023", "N/A", D8 - INDEX($D$8:$D$39, MATCH(1, ($A$8:$A$39=A8) * ($B$8:$B$39=(LEFT(B8, 4)-1)&RIGHT(B8, 3)), 0)))} -> N/A | G8: =IF(D8>0.35, "Strong", IF(D8>=0.2, "Moderate", "At Risk")) -> Strong
A9: Widget Pro | B9: 2023 Q2 | C9: =SUMIFS('Raw Data'!E:E, 'Raw Data'!D:D, A9, 'Raw Data'!B:B, LEFT(B9,4), 'Raw Data'!C:C, RIGHT(B9,2)) -> 158778 | D9: {=SUMPRODUCT(('Raw Data'!$D$2:$D$500=A9)*('Raw Data'!$B$2:$B$500&" "&'Raw Data'!$C$2:$C$500=B9)*('Raw Data'!$G$2:$G$500))/C9} -> 0.35548514 | E9: =IF(B9="2023 Q1", "N/A", D9-D8) -> -0.020821992 | F9: {=IF(LEFT(B9, 4)="2023", "N/A", D9 - INDEX($D$8:$D$39, MATCH(1, ($A$8:$A$39=A9) * ($B$8:$B$39=(LEFT(B9, 4)-1)&RIGHT(B9, 3)), 0)))} -> N/A | G9: =IF(D9>0.35, "Strong", IF(D9>=0.2, "Moderate", "At Risk")) -> Strong
A10: Widget Pro | B10: 2023 Q3 | C10: =SUMIFS('Raw Data'!E:E, 'Raw Data'!D:D, A10, 'Raw Data'!B:B, LEFT(B10,4), 'Raw Data'!C:C, RIGHT(B10,2)) -> 139128 | D10: {=SUMPRODUCT(('Raw Data'!$D$2:$D$500=A10)*('Raw Data'!$B$2:$B$500&" "&'Raw Data'!$C$2:$C$500=B10)*('Raw Data'!$G$2:$G$500))/C10} -> 0.36162634 | E10: =IF(B10="2023 Q1", "N/A", D10-D9) -> 0.0061412013 | F10: {=IF(LEFT(B10, 4)="2023", "N/A", D10 - INDEX($D$8:$D$39, MATCH(1, ($A$8:$A$39=A10) * ($B$8:$B$39=(LEFT(B10, 4)-1)&RIGHT(B10, 3)), 0)))} -> N/A | G10: =IF(D10>0.35, "Strong", IF(D10>=0.2, "Moderate", "At Risk")) -> Strong
A11: Widget Pro | B11: 2023 Q4 | C11: =SUMIFS('Raw Data'!E:E, 'Raw Data'!D:D, A11, 'Raw Data'!B:B, LEFT(B11,4), 'Raw Data'!C:C, RIGHT(B11,2)) -> 195263 | D11: {=SUMPRODUCT(('Raw Data'!$D$2:$D$500=A11)*('Raw Data'!$B$2:$B$500&" "&'Raw Data'!$C$2:$C$500=B11)*('Raw Data'!$G$2:$G$500))/C11} -> 0.38824432 | E11: =IF(B11="2023 Q1", "N/A", D11-D10) -> 0.026617973 | F11: {=IF(LEFT(B11, 4)="2023", "N/A", D11 - INDEX($D$8:$D$39, MATCH(1, ($A$8:$A$39=A11) * ($B$8:$B$39=(LEFT(B11, 4)-1)&RIGHT(B11, 3)), 0)))} -> N/A | G11: =IF(D11>0.35, "Strong", IF(D11>=0.2, "Moderate", "At Risk")) -> Strong
A12: Widget Pro | B12: 2024 Q1 | C12: =SUMIFS('Raw Data'!E:E, 'Raw Data'!D:D, A12, 'Raw Data'!B:B, LEFT(B12,4), 'Raw Data'!C:C, RIGHT(B12,2)) -> 230966 | D12: {=SUMPRODUCT(('Raw Data'!$D$2:$D$500=A12)*('Raw Data'!$B$2:$B$500&" "&'Raw Data'!$C$2:$C$500=B12)*('Raw Data'!$G$2:$G$500))/C12} -> 0.39270096 | E12: =IF(B12="2023 Q1", "N/A", D12-D11) -> 0.0044566437 | F12: {=IF(LEFT(B12, 4)="2023", "N/A", D12 - INDEX($D$8:$D$39, MATCH(1, ($A$8:$A$39=A12) * ($B$8:$B$39=(LEFT(B12, 4)-1)&RIGHT(B12, 3)), 0)))} -> 0.016393826 | G12: =IF(D12>0.35, "Strong", IF(D12>=0.2, "Moderate", "At Risk")) -> Strong
A13: Widget Pro | B13: 2024 Q2 | C13: =SUMIFS('Raw Data'!E:E, 'Raw Data'!D:D, A13, 'Raw Data'!B:B, LEFT(B13,4), 'Raw Data'!C:C, RIGHT(B13,2)) -> 142170 | D13: {=SUMPRODUCT(('Raw Data'!$D$2:$D$500=A13)*('Raw Data'!$B$2:$B$500&" "&'Raw Data'!$C$2:$C$500=B13)*('Raw Data'!$G$2:$G$500))/C13} -> 0.41061813 | E13: =IF(B13="2023 Q1", "N/A", D13-D12) -> 0.017917173 | F13: {=IF(LEFT(B13, 4)="2023", "N/A", D13 - INDEX($D$8:$D$39, MATCH(1, ($A$8:$A$39=A13) * ($B$8:$B$39=(LEFT(B13, 4)-1)&RIGHT(B13, 3)), 0)))} -> 0.05513299 | G13: =IF(D13>0.35, "Strong", IF(D13>=0.2, "Moderate", "At Risk")) -> Strong
A14: Widget Pro | B14: 2024 Q3 | C14: =SUMIFS('Raw Data'!E:E, 'Raw Data'!D:D, A14, 'Raw Data'!B:B, LEFT(B14,4), 'Raw Data'!C:C, RIGHT(B14,2)) -> 196327 | D14: {=SUMPRODUCT(('Raw Data'!$D$2:$D$500=A14)*('Raw Data'!$B$2:$B$500&" "&'Raw Data'!$C$2:$C$500=B14)*('Raw Data'!$G$2:$G$500))/C14} -> 0.40558334 | E14: =IF(B14="2023 Q1", "N/A", D14-D13) -> -0.0050347952 | F14: {=IF(LEFT(B14, 4)="2023", "N/A", D14 - INDEX($D$8:$D$39, MATCH(1, ($A$8:$A$39=A14) * ($B$8:$B$39=(LEFT(B14, 4)-1)&RIGHT(B14, 3)), 0)))} -> 0.043956994 | G14: =IF(D14>0.35, "Strong", IF(D14>=0.2, "Moderate", "At Risk")) -> Strong
A15: Widget Pro | B15: 2024 Q4 | C15: =SUMIFS('Raw Data'!E:E, 'Raw Data'!D:D, A15, 'Raw Data'!B:B, LEFT(B15,4), 'Raw Data'!C:C, RIGHT(B15,2)) -> 156548 | D15: {=SUMPRODUCT(('Raw Data'!$D$2:$D$500=A15)*('Raw Data'!$B$2:$B$500&" "&'Raw Data'!$C$2:$C$500=B15)*('Raw Data'!$G$2:$G$500))/C15} -> 0.39827554 | E15: =IF(B15="2023 Q1", "N/A", D15-D14) -> -0.0073077931 | F15: {=IF(LEFT(B15, 4)="2023", "N/A", D15 - INDEX($D$8:$D$39, MATCH(1, ($A$8:$A$39=A15) * ($B$8:$B$39=(LEFT(B15, 4)-1)&RIGHT(B15, 3)), 0)))} -> 0.010031228 | G15: =IF(D15>0.35, "Strong", IF(D15>=0.2, "Moderate", "At Risk")) -> Strong
A16: Widget Standard | B16: 2023 Q1 | C16: =SUMIFS('Raw Data'!E:E, 'Raw Data'!D:D, A16, 'Raw Data'!B:B, LEFT(B16,4), 'Raw Data'!C:C, RIGHT(B16,2)) -> 71969 | D16: {=SUMPRODUCT(('Raw Data'!$D$2:$D$500=A16)*('Raw Data'!$B$2:$B$500&" "&'Raw Data'!$C$2:$C$500=B16)*('Raw Data'!$G$2:$G$500))/C16} -> 0.26717364 | E16: =IF(B16="2023 Q1", "N/A", D16-D15) -> N/A | F16: {=IF(LEFT(B16, 4)="2023", "N/A", D16 - INDEX($D$8:$D$39, MATCH(1, ($A$8:$A$39=A16) * ($B$8:$B$39=(LEFT(B16, 4)-1)&RIGHT(B16, 3)), 0)))} -> N/A | G16: =IF(D16>0.35, "Strong", IF(D16>=0.2, "Moderate", "At Risk")) -> Moderate
A17: Widget Standard | B17: 2023 Q2 | C17: =SUMIFS('Raw Data'!E:E, 'Raw Data'!D:D, A17, 'Raw Data'!B:B, LEFT(B17,4), 'Raw Data'!C:C, RIGHT(B17,2)) -> 88594 | D17: {=SUMPRODUCT(('Raw Data'!$D$2:$D$500=A17)*('Raw Data'!$B$2:$B$500&" "&'Raw Data'!$C$2:$C$500=B17)*('Raw Data'!$G$2:$G$500))/C17} -> 0.26956882 | E17: =IF(B17="2023 Q1", "N/A", D17-D16) -> 0.0023951754 | F17: {=IF(LEFT(B17, 4)="2023", "N/A", D17 - INDEX($D$8:$D$39, MATCH(1, ($A$8:$A$39=A17) * ($B$8:$B$39=(LEFT(B17, 4)-1)&RIGHT(B17, 3)), 0)))} -> N/A | G17: =IF(D17>0.35, "Strong", IF(D17>=0.2, "Moderate", "At Risk")) -> Moderate
A18: Widget Standard | B18: 2023 Q3 | C18: =SUMIFS('Raw Data'!E:E, 'Raw Data'!D:D, A18, 'Raw Data'!B:B, LEFT(B18,4), 'Raw Data'!C:C, RIGHT(B18,2)) -> 122105 | D18: {=SUMPRODUCT(('Raw Data'!$D$2:$D$500=A18)*('Raw Data'!$B$2:$B$500&" "&'Raw Data'!$C$2:$C$500=B18)*('Raw Data'!$G$2:$G$500))/C18} -> 0.27581991 | E18: =IF(B18="2023 Q1", "N/A", D18-D17) -> 0.0062510895 | F18: {=IF(LEFT(B18, 4)="2023", "N/A", D18 - INDEX($D$8:$D$39, MATCH(1, ($A$8:$A$39=A18) * ($B$8:$B$39=(LEFT(B18, 4)-1)&RIGHT(B18, 3)), 0)))} -> N/A | G18: =IF(D18>0.35, "Strong", IF(D18>=0.2, "Moderate", "At Risk")) -> Moderate
A19: Widget Standard | B19: 2023 Q4 | C19: =SUMIFS('Raw Data'!E:E, 'Raw Data'!D:D, A19, 'Raw Data'!B:B, LEFT(B19,4), 'Raw Data'!C:C, RIGHT(B19,2)) -> 151829 | D19: {=SUMPRODUCT(('Raw Data'!$D$2:$D$500=A19)*('Raw Data'!$B$2:$B$500&" "&'Raw Data'!$C$2:$C$500=B19)*('Raw Data'!$G$2:$G$500))/C19} -> 0.2990567 | E19: =IF(B19="2023 Q1", "N/A", D19-D18) -> 0.023236793 | F19: {=IF(LEFT(B19, 4)="2023", "N/A", D19 - INDEX($D$8:$D$39, MATCH(1, ($A$8:$A$39=A19) * ($B$8:$B$39=(LEFT(B19, 4)-1)&RIGHT(B19, 3)), 0)))} -> N/A | G19: =IF(D19>0.35, "Strong", IF(D19>=0.2, "Moderate", "At Risk")) -> Moderate
... A39: Accessory Kit | B39: 2024 Q4 | C39: =SUMIFS('Raw Data'!E:E, 'Raw Data'!D:D, A39, 'Raw Data'!B:B, LEFT(B39,4), 'Raw Data'!C:C, RIGHT(B39,2)) -> 35036 | D39: {=SUMPRODUCT(('Raw Data'!$D$2:$D$500=A39)*('Raw Data'!$B$2:$B$500&" "&'Raw Data'!$C$2:$C$500=B39)*('Raw Data'!$G$2:$G$500))/C39} -> 0.18999657 | E39: =IF(B39="2023 Q1", "N/A", D39-D38) -> -0.026720866 | F39: {=IF(LEFT(B39, 4)="2023", "N/A", D39 - INDEX($D$8:$D$39, MATCH(1, ($A$8:$A$39=A39) * ($B$8:$B$39=(LEFT(B39, 4)-1)&RIGHT(B39, 3)), 0)))} -> -0.0033561789 | G39: =IF(D39>0.35, "Strong", IF(D39>=0.2, "Moderate", "At Risk")) -> At Risk
A42: Chart Data
A43: Quarter | B43: Widget Pro | C43: Widget Standard | D43: Service Package | E43: Accessory Kit | F43: Total Revenue
A44: 2023 Q1 | B44: {=SUMPRODUCT(($A$8:$A$39=B$43)*($B$8:$B$39=$A44)*($D$8:$D$39))} -> 0.37630713 | C44: {=SUMPRODUCT(($A$8:$A$39=C$43)*($B$8:$B$39=$A44)*($D$8:$D$39))} -> 0.26717364 | D44: {=SUMPRODUCT(($A$8:$A$39=D$43)*($B$8:$B$39=$A44)*($D$8:$D$39))} -> 0.39424928 | E44: {=SUMPRODUCT(($A$8:$A$39=E$43)*($B$8:$B$39=$A44)*($D$8:$D$39))} -> 0.18221599
A45: 2023 Q2 | B45: {=SUMPRODUCT(($A$8:$A$39=B$43)*($B$8:$B$39=$A45)*($D$8:$D$39))} -> 0.35548514 | C45: {=SUMPRODUCT(($A$8:$A$39=C$43)*($B$8:$B$39=$A45)*($D$8:$D$39))} -> 0.26956882 | D45: {=SUMPRODUCT(($A$8:$A$39=D$43)*($B$8:$B$39=$A45)*($D$8:$D$39))} -> 0.47396217 | E45: {=SUMPRODUCT(($A$8:$A$39=E$43)*($B$8:$B$39=$A45)*($D$8:$D$39))} -> 0.18293272 | F45: =SUMIF($B$8:$B$39, $A45, $C$8:$C$39) -> 371333
A46: 2023 Q3 | B46: {=SUMPRODUCT(($A$8:$A$39=B$43)*($B$8:$B$39=$A46)*($D$8:$D$39))} -> 0.36162634 | C46: {=SUMPRODUCT(($A$8:$A$39=C$43)*($B$8:$B$39=$A46)*($D$8:$D$39))} -> 0.27581991 | D46: {=SUMPRODUCT(($A$8:$A$39=D$43)*($B$8:$B$39=$A46)*($D$8:$D$39))} -> 0.44135011 | E46: {=SUMPRODUCT(($A$8:$A$39=E$43)*($B$8:$B$39=$A46)*($D$8:$D$39))} -> 0.17840851 | F46: =SUMIF($B$8:$B$39, $A46, $C$8:$C$39) -> 354408
A47: 2023 Q4 | B47: {=SUMPRODUCT(($A$8:$A$39=B$43)*($B$8:$B$39=$A47)*($D$8:$D$39))} -> 0.38824432 | C47: {=SUMPRODUCT(($A$8:$A$39=C$43)*($B$8:$B$39=$A47)*($D$8:$D$39))} -> 0.2990567 | D47: {=SUMPRODUCT(($A$8:$A$39=D$43)*($B$8:$B$39=$A47)*($D$8:$D$39))} -> 0.39682713 | E47: {=SUMPRODUCT(($A$8:$A$39=E$43)*($B$8:$B$39=$A47)*($D$8:$D$39))} -> 0.19335275 | F47: =SUMIF($B$8:$B$39, $A47, $C$8:$C$39) -> 403216
A48: 2024 Q1 | B48: {=SUMPRODUCT(($A$8:$A$39=B$43)*($B$8:$B$39=$A48)*($D$8:$D$39))} -> 0.39270096 | C48: {=SUMPRODUCT(($A$8:$A$39=C$43)*($B$8:$B$39=$A48)*($D$8:$D$39))} -> 0.29513703 | D48: {=SUMPRODUCT(($A$8:$A$39=D$43)*($B$8:$B$39=$A48)*($D$8:$D$39))} -> 0.42219207 | E48: {=SUMPRODUCT(($A$8:$A$39=E$43)*($B$8:$B$39=$A48)*($D$8:$D$39))} -> 0.19668577 | F48: =SUMIF($B$8:$B$39, $A48, $C$8:$C$39) -> 472182
A49: 2024 Q2 | B49: {=SUMPRODUCT(($A$8:$A$39=B$43)*($B$8:$B$39=$A49)*($D$8:$D$39))} -> 0.41061813 | C49: {=SUMPRODUCT(($A$8:$A$39=C$43)*($B$8:$B$39=$A49)*($D$8:$D$39))} -> 0.30790755 | D49: {=SUMPRODUCT(($A$8:$A$39=D$43)*($B$8:$B$39=$A49)*($D$8:$D$39))} -> 0.5006934 | E49: {=SUMPRODUCT(($A$8:$A$39=E$43)*($B$8:$B$39=$A49)*($D$8:$D$39))} -> 0.21247087 | F49: =SUMIF($B$8:$B$39, $A49, $C$8:$C$39) -> 309241
A50: 2024 Q3 | B50: {=SUMPRODUCT(($A$8:$A$39=B$43)*($B$8:$B$39=$A50)*($D$8:$D$39))} -> 0.40558334 | C50: {=SUMPRODUCT(($A$8:$A$39=C$43)*($B$8:$B$39=$A50)*($D$8:$D$39))} -> 0.32837755 | D50: {=SUMPRODUCT(($A$8:$A$39=D$43)*($B$8:$B$39=$A50)*($D$8:$D$39))} -> 0.44809206 | E50: {=SUMPRODUCT(($A$8:$A$39=E$43)*($B$8:$B$39=$A50)*($D$8:$D$39))} -> 0.21671744 | F50: =SUMIF($B$8:$B$39, $A50, $C$8:$C$39) -> 326636
A51: 2024 Q4 | B51: {=SUMPRODUCT(($A$8:$A$39=B$43)*($B$8:$B$39=$A51)*($D$8:$D$39))} -> 0.39827554 | C51: {=SUMPRODUCT(($A$8:$A$39=C$43)*($B$8:$B$39=$A51)*($D$8:$D$39))} -> 0.31844897 | D51: {=SUMPRODUCT(($A$8:$A$39=D$43)*($B$8:$B$39=$A51)*($D$8:$D$39))} -> 0.50698815 | E51: {=SUMPRODUCT(($A$8:$A$39=E$43)*($B$8:$B$39=$A51)*($D$8:$D$39))} -> 0.18999657 | F51: =SUMIF($B$8:$B$39, $A51, $C$8:$C$39) -> 335484
